{
  "animateLoading": true,
  "borderRadius": "{{appsmith.theme.borderRadius.appBorderRadius}}",
  "bottomRow": 259,
  "boxShadow": "none",
  "canEscapeKeyClose": true,
  "canOutsideClickClose": true,
  "children": [
    {
      "bottomRow": 670,
      "canExtend": true,
      "detachFromLayout": true,
      "displayName": "Canvas",
      "dynamicBindingPathList": [],
      "flexLayers": [],
      "hideCard": true,
      "isDeprecated": false,
      "isDisabled": false,
      "isLoading": false,
      "isVisible": true,
      "key": "8wv32k8835",
      "leftColumn": 0,
      "minHeight": 672,
      "minWidth": 450,
      "mobileBottomRow": 240,
      "mobileLeftColumn": 0,
      "mobileRightColumn": 300,
      "mobileTopRow": 0,
      "parentColumnSpace": 1,
      "parentId": "e9u2f9m07l",
      "parentRowSpace": 1,
      "renderMode": "CANVAS",
      "responsiveBehavior": "fill",
      "rightColumn": 300,
      "shouldScrollContents": false,
      "topRow": 0,
      "type": "CANVAS_WIDGET",
      "version": 1,
      "widgetId": "yo1ka7ocrv",
      "widgetName": "Canvas22"
    }
  ],
  "detachFromLayout": true,
  "displayName": "Modal",
  "dynamicBindingPathList": [
    {
      "key": "borderRadius"
    }
  ],
  "dynamicHeight": "FIXED",
  "dynamicTriggerPathList": [],
  "height": 672,
  "hideCard": false,
  "iconSVG": "/static/media/icon.4975978e9a961fb0bfb4e38de7ecc7c5.svg",
  "isCanvas": true,
  "isDeprecated": false,
  "isLoading": false,
  "key": "a5ta74rv7j",
  "leftColumn": 13,
  "maxDynamicHeight": 9000,
  "minDynamicHeight": 24,
  "mobileBottomRow": 43,
  "mobileLeftColumn": 13,
  "mobileRightColumn": 37,
  "mobileTopRow": 19,
  "parentColumnSpace": 12.5,
  "parentId": "0",
  "parentRowSpace": 10,
  "renderMode": "CANVAS",
  "rightColumn": 37,
  "searchTags": [
    "dialog",
    "popup",
    "notification"
  ],
  "shouldScrollContents": true,
  "topRow": 19,
  "type": "MODAL_WIDGET",
  "version": 2,
  "widgetId": "e9u2f9m07l",
  "widgetName": "Modal6",
  "width": 956
}