{
  "animateLoading": true,
  "borderRadius": "{{appsmith.theme.borderRadius.appBorderRadius}}",
  "bottomRow": 4,
  "displayName": "Text",
  "dynamicBindingPathList": [
    {
      "key": "truncateButtonColor"
    },
    {
      "key": "fontFamily"
    },
    {
      "key": "borderRadius"
    },
    {
      "key": "text"
    }
  ],
  "dynamicHeight": "FIXED",
  "dynamicTriggerPathList": [],
  "fontFamily": "{{appsmith.theme.fontFamily.appFont}}",
  "fontSize": "0.875rem",
  "fontStyle": "BOLD",
  "hideCard": false,
  "iconSVG": "/static/media/icon.97c59b523e6f70ba6f40a10fc2c7c5b5.svg",
  "isDeprecated": false,
  "isLoading": false,
  "isVisible": true,
  "key": "yssxm4c2g3",
  "leftColumn": 10,
  "maxDynamicHeight": 9000,
  "minDynamicHeight": 4,
  "minWidth": 450,
  "mobileBottomRow": 4,
  "mobileLeftColumn": 12,
  "mobileRightColumn": 28,
  "mobileTopRow": 0,
  "overflow": "NONE",
  "parentColumnSpace": 14.09375,
  "parentId": "nf781zskvx",
  "parentRowSpace": 10,
  "renderMode": "CANVAS",
  "responsiveBehavior": "fill",
  "rightColumn": 64,
  "searchTags": [
    "typography",
    "paragraph",
    "label"
  ],
  "shouldTruncate": false,
  "text": "{{currentItem.type == 1? currentItem.create_by+\",已确认\": currentItem.type == 2? currentItem.create_by+\"，处理为已解决,\"+currentItem.follow_record: currentItem.type == 3? currentItem.create_by+\"，处理为不予解决,\"+currentItem.follow_record: currentItem.type == 4? currentItem.create_by+\"，处理为重新激活,\"+currentItem.follow_record: currentItem.type == 6? currentItem.create_by+\"，处理为关闭,\"+currentItem.follow_record: currentItem.create_by+\"，添加评论,\"+ currentItem.follow_record}}",
  "textAlign": "LEFT",
  "textColor": "#231F20",
  "topRow": 0,
  "truncateButtonColor": "{{appsmith.theme.colors.primaryColor}}",
  "type": "TEXT_WIDGET",
  "version": 1,
  "widgetId": "0efecspind",
  "widgetName": "Text5"
}