{
  "animateLoading": true,
  "backgroundColor": "white",
  "borderColor": "#E0DEDE",
  "borderRadius": "{{appsmith.theme.borderRadius.appBorderRadius}}",
  "borderWidth": "1",
  "bottomRow": 10,
  "boxShadow": "{{appsmith.theme.boxShadow.appBoxShadow}}",
  "children": [
    {
      "bottomRow": 100,
      "canExtend": false,
      "containerStyle": "none",
      "detachFromLayout": true,
      "displayName": "Canvas",
      "dynamicBindingPathList": [],
      "hideCard": true,
      "isDeprecated": false,
      "isLoading": false,
      "isVisible": true,
      "key": "mqabop0im6",
      "leftColumn": 0,
      "minHeight": 100,
      "parentColumnSpace": 1,
      "parentId": "h54hunz4lq",
      "parentRowSpace": 1,
      "renderMode": "CANVAS",
      "topRow": 0,
      "type": "CANVAS_WIDGET",
      "version": 1,
      "widgetId": "23s3sp99yq",
      "widgetName": "Canvas20"
    }
  ],
  "containerStyle": "card",
  "disablePropertyPane": true,
  "disabledWidgetFeatures": [
    "dynamicHeight"
  ],
  "disallowCopy": true,
  "displayName": "Container",
  "dragDisabled": true,
  "dynamicBindingPathList": [
    {
      "key": "borderRadius"
    },
    {
      "key": "boxShadow"
    }
  ],
  "dynamicHeight": "FIXED",
  "hideCard": false,
  "iconSVG": "/static/media/icon.1977dca3370505e2db3a8e44cfd54907.svg",
  "isCanvas": true,
  "isDeletable": false,
  "isDeprecated": false,
  "isLoading": false,
  "isVisible": true,
  "key": "he6fa7xev7",
  "leftColumn": 0,
  "maxDynamicHeight": 9000,
  "minDynamicHeight": 10,
  "openParentPropertyPane": true,
  "parentId": "niclfgiedw",
  "renderMode": "CANVAS",
  "rightColumn": 64,
  "searchTags": [
    "div",
    "parent",
    "group"
  ],
  "shouldScrollContents": true,
  "topRow": 0,
  "type": "CONTAINER_WIDGET",
  "version": 1,
  "widgetId": "h54hunz4lq",
  "widgetName": "Container5"
}