{
  "gitSyncId": "636b1198aaab6224b941b41b_636e0db9e6a0be457fd9c5b7",
  "id": "项目详情_sProject_task",
  "pluginId": "mysql-plugin",
  "pluginType": "DB",
  "unpublishedAction": {
    "actionConfiguration": {
      "body": "SELECT * FROM t_project_task where project_id = {{appsmith.store.project_id}} AND existence != 0;",
      "encodeParamsToggle": true,
      "paginationType": "NONE",
      "pluginSpecifiedTemplates": [
        {
          "value": true
        }
      ],
      "timeoutInMillisecond": 10000
    },
    "confirmBeforeExecute": false,
    "datasource": {
      "id": "local_mysql",
      "isAutoGenerated": false,
      "name": "local_mysql",
      "pluginId": "mysql-plugin"
    },
    "dynamicBindingPathList": [
      {
        "key": "body"
      }
    ],
    "name": "sProject_task",
    "pageId": "项目详情",
    "runBehaviour": "MANUAL",
    "userSetOnLoad": false
  }
}