{
  "accentColor": "{{appsmith.theme.colors.primaryColor}}",
  "animateLoading": true,
  "autoFocus": false,
  "borderRadius": "{{appsmith.theme.borderRadius.appBorderRadius}}",
  "bottomRow": 26,
  "boxShadow": "none",
  "defaultText": "",
  "displayName": "输入框",
  "dynamicBindingPathList": [
    {
      "key": "accentColor"
    },
    {
      "key": "borderRadius"
    }
  ],
  "dynamicHeight": "FIXED",
  "dynamicTriggerPathList": [],
  "hideCard": false,
  "iconAlign": "left",
  "iconSVG": "/static/media/icon.9f505595da61a34f563dba82adeb06ec.svg",
  "inputType": "MULTI_LINE_TEXT",
  "isDeprecated": false,
  "isDisabled": false,
  "isLoading": false,
  "isRequired": true,
  "isVisible": true,
  "key": "7626umhfih",
  "label": "备注说明：",
  "labelAlignment": "left",
  "labelPosition": "Auto",
  "labelStyle": "",
  "labelTextSize": "0.875rem",
  "labelWidth": 5,
  "leftColumn": 3,
  "maxDynamicHeight": 9000,
  "minDynamicHeight": 4,
  "parentColumnSpace": 8.34375,
  "parentId": "i8qbofzhbn",
  "parentRowSpace": 10,
  "renderMode": "CANVAS",
  "resetOnSubmit": true,
  "rightColumn": 57,
  "searchTags": [
    "form",
    "text input",
    "number",
    "textarea"
  ],
  "topRow": 7,
  "type": "INPUT_WIDGET_V2",
  "version": 2,
  "widgetId": "qzbz50m23s",
  "widgetName": "Input1"
}