{
  "animateLoading": false,
  "borderRadius": "{{appsmith.theme.borderRadius.appBorderRadius}}",
  "bottomRow": 4,
  "boxShadow": "none",
  "buttonColor": "{{appsmith.theme.colors.primaryColor}}",
  "buttonVariant": "TERTIARY",
  "disabledWhenInvalid": false,
  "displayName": "Button",
  "dynamicBindingPathList": [
    {
      "key": "buttonColor"
    },
    {
      "key": "borderRadius"
    }
  ],
  "dynamicTriggerPathList": [
    {
      "key": "onClick"
    }
  ],
  "hideCard": false,
  "iconAlign": "left",
  "iconName": "cross",
  "iconSVG": "/static/media/icon.cca026338f1c8eb6df8ba03d084c2fca.svg",
  "isDefaultClickDisabled": true,
  "isDeprecated": false,
  "isDisabled": false,
  "isLoading": false,
  "isVisible": true,
  "key": "79p07f1826",
  "leftColumn": 60,
  "onClick": "{{navigateTo('巡检用例', {})}}",
  "parentColumnSpace": 14.0625,
  "parentId": "0",
  "parentRowSpace": 10,
  "placement": "CENTER",
  "recaptchaType": "V3",
  "renderMode": "CANVAS",
  "resetFormOnClick": false,
  "rightColumn": 64,
  "searchTags": [
    "click",
    "submit"
  ],
  "text": "",
  "topRow": 0,
  "type": "BUTTON_WIDGET",
  "version": 1,
  "widgetId": "lqc2fgvolf",
  "widgetName": "Button1"
}