{
  "animateLoading": true,
  "backgroundColor": "white",
  "borderColor": "#E0DEDE",
  "borderRadius": "{{appsmith.theme.borderRadius.appBorderRadius}}",
  "borderWidth": "1",
  "bottomRow": 18,
  "boxShadow": "{{appsmith.theme.boxShadow.appBoxShadow}}",
  "children": [
    {
      "borderRadius": "{{appsmith.theme.borderRadius.appBorderRadius}}",
      "bottomRow": 140,
      "boxShadow": "{{appsmith.theme.boxShadow.appBoxShadow}}",
      "canExtend": false,
      "containerStyle": "none",
      "detachFromLayout": true,
      "dynamicBindingPathList": [
        {
          "key": "borderRadius"
        },
        {
          "key": "boxShadow"
        }
      ],
      "dynamicHeight": "AUTO_HEIGHT",
      "flexLayers": [],
      "isLoading": false,
      "isVisible": true,
      "key": "ers8hrcbzq",
      "leftColumn": 0,
      "maxDynamicHeight": 9000,
      "minDynamicHeight": 4,
      "minHeight": 140,
      "minWidth": 450,
      "mobileBottomRow": 140,
      "mobileLeftColumn": 0,
      "mobileRightColumn": 445.5,
      "mobileTopRow": 0,
      "needsErrorInfo": false,
      "parentColumnSpace": 1,
      "parentId": "47591upbe0",
      "parentRowSpace": 1,
      "renderMode": "CANVAS",
      "responsiveBehavior": "fill",
      "rightColumn": 445.5,
      "topRow": 0,
      "type": "CANVAS_WIDGET",
      "version": 1,
      "widgetId": "zilkjdnymt",
      "widgetName": "Canvas1CopyCopy"
    }
  ],
  "dynamicBindingPathList": [
    {
      "key": "borderRadius"
    },
    {
      "key": "boxShadow"
    }
  ],
  "dynamicHeight": "AUTO_HEIGHT",
  "flexVerticalAlignment": "stretch",
  "isCanvas": true,
  "isLoading": false,
  "isVisible": true,
  "key": "rudkf5mwb7",
  "leftColumn": 33,
  "maxDynamicHeight": 9000,
  "minDynamicHeight": 10,
  "mobileBottomRow": 14,
  "mobileLeftColumn": 2,
  "mobileRightColumn": 24,
  "mobileTopRow": 0,
  "needsErrorInfo": false,
  "originalBottomRow": 18,
  "originalTopRow": 4,
  "parentColumnSpace": 20.25,
  "parentId": "0",
  "parentRowSpace": 10,
  "positioning": "fixed",
  "renderMode": "CANVAS",
  "responsiveBehavior": "fill",
  "rightColumn": 43,
  "shouldScrollContents": true,
  "topRow": 4,
  "type": "STATBOX_WIDGET",
  "widgetId": "47591upbe0",
  "widgetName": "Statbox3"
}